vistool/__init__.py
vistool/combine.py
vistool/download.py
vistool/visualize.py
vistool/wrangle.py
vistool-0.1.1.dist-info/METADATA
vistool-0.1.1.dist-info/WHEEL
vistool-0.1.1.dist-info/licenses/LICENSE
vistool-0.1.1.dist-info/RECORD
