Metadata-Version: 2.4
Name: vistool
Version: 0.1.1
Summary: A Python package for data analysis, cleaning, and visualization.
Project-URL: Homepage, https://github.com/KaysHaydock/VisTool/tree/main
Author-email: Guled Abdullahi <gissa8991@gmail.com>, Kayleigh Haydock <kayz_haydock@hotmail.co.uk>
License-Expression: MIT
License-File: LICENSE
Classifier: License :: OSI Approved :: MIT License
Classifier: Operating System :: OS Independent
Classifier: Programming Language :: Python :: 3.8
Classifier: Programming Language :: Python :: 3.9
Classifier: Programming Language :: Python :: 3.10
Classifier: Programming Language :: Python :: 3.11
Classifier: Programming Language :: Python :: 3.12
Requires-Python: >=3.8
Requires-Dist: matplotlib>=3.1.3
Requires-Dist: numpy>=1.26.1
Requires-Dist: pandas>=2.0.1
Requires-Dist: panel>=0.14.0
Requires-Dist: seaborn>=0.12.2
